{
  "placeholderImages": [
    {
      "id": "foto_1",
      "description": "Navidad juntos 🎅",
      "imageUrl": "/images/foto1.jpeg"
    },
    {
      "id": "foto_2",
      "description": "Tu cumple",
      "imageUrl": "/images/foto2.jpeg"
    },
    {
      "id": "foto_3",
      "description": "Viajecito 🌳",
      "imageUrl": "/images/foto3.jpeg"
    },
    {
      "id": "foto_4",
      "description": "Ra rauw 🕺",
      "imageUrl": "/images/foto4.jpeg"
    },
    {
      "id": "foto_5",
      "description": "Halloween 🎃",
      "imageUrl": "/images/foto5.jpeg"
    },
    {
      "id": "foto_6",
      "description": "Date de ballet 🌃",
      "imageUrl": "/images/foto6.jpeg"
    },
    {
      "id": "foto_7",
      "description": "Otra de tu cumple 🎂",
      "imageUrl": "/images/foto7.jpeg"
    },
    {
      "id": "foto_8",
      "description": "Pedida :)",
      "imageUrl": "/images/foto8.jpeg"
    }
  ]
}
